Arqui/S3/Mux2a1/Mux2a1.srcs/sources_1/new/Mux2a1.v
`timescale 1ns / 1ps
//////////////////////////////////////////////////////////////////////////////////
// Company: 
// Engineer: 
// 
// Create Date: 02.09.2023 10:18:04
// Design Name: 
// Module Name: Mux2a1
// Project Name: 
// Target Devices: 
// Tool Versions: 
// Description: 
// 
// Dependencies: 
// 
// Revision:
// Revision 0.01 - File Created
// Additional Comments:
// 
//////////////////////////////////////////////////////////////////////////////////


module Mux2a1(a0, a1, s, y);
    input a0, a1, s;
    output y;
    reg y; // va a poder modificarse

    always @(s or a0 or a1) begin
        // Como un ifelse, 
            // cuando s es 0 y es a0
            // cuando s es 1 y es a1
        case (s)
            1'b0: y = a0;
            1'b1: y = a1;
        endcase
    end
endmodule

/*
module Mux2a1(a0,a1,s,y);
    input a0, a1, s;
    output y;
    reg y;

    always @(s or a0 or a1) begin
        case (s)
            1'b1: y = a1;
            default: y = a0;
        endcase
    end
endmodule
*/

// Mux2a1 behavioral
// module Mux2a1(a0, a1, s, y);
//     input a0, a1, s;
//     output y;

//     assign y = a0 & ~s | a1 & s;
// endmodule

Arqui/S3/Mux2a1/Mux2a1.srcs/sim_1/new/Mux2a1_tb.v
`timescale 1ns / 1ps
//////////////////////////////////////////////////////////////////////////////////
// Company: 
// Engineer: 
// 
// Create Date: 02.09.2023 10:33:04
// Design Name: 
// Module Name: Mux2a1_tb
// Project Name: 
// Target Devices: 
// Tool Versions: 
// Description: 
// 
// Dependencies: 
// 
// Revision:
// Revision 0.01 - File Created
// Additional Comments:
// 
//////////////////////////////////////////////////////////////////////////////////


module Mux2a1_tb;

    reg d0, d1, s;
    wire y;

    Mux2a1 test(.a0(d0), .a1(d1), .s(s), .y(y));

    initial begin
        $dumpfile("Mux2a1_tb.vcd"); // Archivo de simulacion para verlo en gtkwave
        $dumpvars(0, Mux2a1_tb); 

        d0 = 1'b0;
        d1 = 1'b0;
        s = 1'b0;
        #80 $finish;
    end

    always #40 d0 = ~d0;
    always #20 d1 = ~d1;
    always #10 s = ~s;

    initial begin
        // El monitor es para escribir en consola los valores de las variables
        $monitor("%2d:\ta=%b\tb=%b\ts=%b\ty=%b", $time, d0, d1, s, y);
    end

endmodule

Arqui/S3/Mux2a1/Mux2a1.sim/sim_1/behav/xsim/Mux2a1_tb.vcd
$date
   Sat Sep  2 10:45:45 2023
$end
$version
  2022.2
$end
$timescale
  1ps
$end
$scope module Mux2a1_tb $end
$var reg 1 ! d0 $end
$var reg 1 " d1 $end
$var reg 1 # s $end
$var wire 1 $ y $end
$scope module test $end
$var wire 1 % a0 $end
$var wire 1 & a1 $end
$var wire 1 ' s $end
$var reg 1 ( y $end
$upscope $end
$upscope $end
$enddefinitions $end
#0
$dumpvars
0!
0"
0#
0$
0%
0&
0'
0(
$end
#10000
1#
1'
0(
#20000
1"
0#
1&
0'
0(
#30000
1#
1$
1'
1(
#40000
1!
0"
0#
1%
0&
0'
1(
#50000
1#
0$
1'
0(
#60000
1"
0#
1$
1&
0'
1(
#70000
1#
1'
1(
